capmatrix/__init__.py
capmatrix/charges.py
capmatrix/core.py
capmatrix/utils.py
arbitrary_capacitance_matrix-0.1.0.dist-info/METADATA
arbitrary_capacitance_matrix-0.1.0.dist-info/WHEEL
arbitrary_capacitance_matrix-0.1.0.dist-info/licenses/LICENSE
arbitrary_capacitance_matrix-0.1.0.dist-info/RECORD
