Metadata-Version: 2.4
Name: arbitrary-capacitance-matrix
Version: 0.1.0
Summary: Compute the capacitance matrix of N conducting spheres using the method of mirror images
Project-URL: Homepage, https://github.com/carlosperezespinar/arbitrary-capacitance-matrix
Project-URL: Documentation, https://github.com/carlosperezespinar/arbitrary-capacitance-matrix
Project-URL: Repository, https://github.com/carlosperezespinar/arbitrary-capacitance-matrix
Project-URL: Issues, https://github.com/carlosperezespinar/arbitrary-capacitance-matrix/issues
Author: Carlos Pérez Espinar, Moisés Pérez Espinosa
License: MIT License
License-File: LICENSE
Keywords: capacitance,electrostatics,mirror-images,physics,spheres
Classifier: Development Status :: 3 - Alpha
Classifier: Intended Audience :: Science/Research
Classifier: License :: OSI Approved :: MIT License
Classifier: Programming Language :: Python :: 3
Classifier: Programming Language :: Python :: 3.9
Classifier: Programming Language :: Python :: 3.10
Classifier: Programming Language :: Python :: 3.11
Classifier: Programming Language :: Python :: 3.12
Classifier: Programming Language :: Python :: 3.13
Classifier: Topic :: Scientific/Engineering :: Physics
Requires-Python: >=3.12
Requires-Dist: numpy>=1.20.0
Provides-Extra: dev
Requires-Dist: black; extra == 'dev'
Requires-Dist: isort; extra == 'dev'
Requires-Dist: pytest-cov; extra == 'dev'
Requires-Dist: pytest>=6.0; extra == 'dev'
Provides-Extra: examples
Requires-Dist: jupyter; extra == 'examples'
Requires-Dist: matplotlib; extra == 'examples'
Requires-Dist: tqdm; extra == 'examples'
